files_dataset/__init__.py
files_dataset/__init__.pyi
files_dataset/compression.py
files_dataset/dataset.py
files_dataset/meta.py
files_dataset-0.1.4.dist-info/METADATA
files_dataset-0.1.4.dist-info/WHEEL
files_dataset-0.1.4.dist-info/top_level.txt
files_dataset-0.1.4.dist-info/RECORD
