Metadata-Version: 2.1
Name: files-dataset
Version: 0.1.4
Summary: Simple, composable standard for storing datasets as one sample per file
Author-email: Marcel Claramunt <marcel@moveread.com>
Project-URL: repo, https://github.com/marciclabas/mltools.git
Requires-Python: >=3.10
Requires-Dist: pydantic
Requires-Dist: haskellian
